{
  "en": [
    {
      "id": "cv",
      "screenshot": "cv.png",
      "title": "My Resume & Portfolio",
      "position": "Personal project",
      "description": "This very site you're visiting. It uses my i18nResume component, to allow you to switch languages and filter my data.",
      "skills": ["React", "TypeScript", "Material UI"],
      "keywords": ["F"],
      "links": [
        {
          "anchor": "Github",
          "url": "https://github.com/eiriarte/cv"
        }
      ]
    },
    {
      "id": "i18nresume",
      "screenshot": "i18nresume.png",
      "title": "i18nResume",
      "position": "Personal project",
      "description": "Open-source React component you can use to render json-resume data with i18n and filtering capabilities.",
      "skills": ["React", "TypeScript", "Tailwind CSS"],
      "keywords": ["F"],
      "links": [
        {
          "anchor": "npm",
          "url": "https://www.npmjs.com/package/i18nresume"
        },
        {
          "anchor": "Github",
          "url": "https://github.com/eiriarte/i18nresume"
        }
      ]
    },
    {
      "id": "kongreso",
      "screenshot": "kongreso.png",
      "title": "Official congress website",
      "position": "Non-profit project",
      "description": "Website for the Spanish National Esperanto Congress in 2023.",
      "skills": ["JavaScript", "Bootstrap", "PHP", "Symfony", "Doctrine", "MySQL"],
      "keywords": ["B", "F"],
      "links": [
        {
          "anchor": "Web",
          "url": "https://kongreso.esperantosevilla.org"
        },
        {
          "anchor": "Github",
          "url": "https://github.com/eiriarte/hk2023"
        }
      ]
    },
    {
      "id": "ase",
      "screenshot": "ASE.png",
      "title": "Official NPO website",
      "position": "Non-profit project",
      "description": "Bilingual website for the Sevillian Esperanto Association with custom WordPress theme.",
      "skills": ["PHP", "WordPress", "JavaScript", "Sass"],
      "keywords": ["F", "B"],
      "links": [
        {
          "anchor": "Web",
          "url": "https://esperantosevilla.org/"
        }
      ]
    },
    {
      "id": "entrellaves",
      "screenshot": "entrellaves.png",
      "title": "Engineering blog",
      "position": "Personal project",
      "description": "My personal blog on web development. Custom WordPress plugin.",
      "skills": ["PHP", "WordPress", "Apache", "Nginx"],
      "keywords": ["B"],
      "links": [
        {
          "anchor": "Web",
          "url": "https://entrellaves.com"
        }
      ]
    },
    {
      "id": "fch",
      "screenshot": "fch.png",
      "title": "Humor website",
      "position": "Side project",
      "description": "Entertainment website with Node.js + MongoDB server (formerly PHP, MySQL and Backbone.js).",
      "skills": ["Node.js", "Express", "MongoDB", "Sass", "PHP", "MySQL", "Backbone.js"],
      "keywords": ["F", "B"],
      "links": [
        {
          "anchor": "Web",
          "url": "https://nosolochistes.com/"
        },
        {
          "anchor": "PHP Version",
          "url": "https://web.archive.org/web/20091207071245/http://feti-chistes.es/"
        },
        {
          "anchor": "Github",
          "url": "https://github.com/eiriarte/nosolochistes"
        }
      ]
    },
    {
      "id": "sng",
      "screenshot": "SNG.png",
      "title": "Educational website",
      "position": "Personal project",
      "description": "Spanish/english educational website for Spanish learners. Hosted in Amazon S3 and CloudFront.",
      "skills": ["JavaScript", "CSS", "Node.js", "AWS"],
      "keywords": ["F", "B"],
      "links": [
        {
          "anchor": "Web",
          "url": "https://spanishnumbers.guide"
        }
      ]
    },
    {
      "id": "numeros",
      "screenshot": "numeros.jpg",
      "title": "Educational app",
      "position": "Side project",
      "description": "Educational Android/iOS app for Spanish learners.",
      "skills": ["React", "React Native"],
      "keywords": ["F"],
      "links": [
        {
          "anchor": "Github",
          "url": "https://github.com/eiriarte/numeros"
        }
      ]
    },
    {
      "id": "vivaverbo",
      "screenshot": "vivaverbo.png",
      "title": "Educational web app",
      "description": "Multi-user tool for language learning using spaced repetition algorithms.",
      "position": "Personal project",
      "skills": ["AngularJS", "Node.js", "MongoDB"],
      "keywords": ["F", "B"],
      "links": [
        {
          "anchor": "Github",
          "url": "https://github.com/eiriarte/vivaverbo"
        },
        {
          "anchor": "Screencast",
          "url": "https://www.youtube.com/watch?v=1BSoZN3Uly8"
        }
      ]
    },
    {
      "id": "andex",
      "screenshot": "andex.png",
      "title": "NGO volunteering app",
      "position": "Non-profit project",
      "description": "Web app to manage volunteer work for the Association ANDEX.",
      "skills": ["CoffeScript", "AngularJS", "Node.js", "Express", "MongoDB", "Sass"],
      "keywords": ["F", "B"],
      "links": [
        {
          "anchor": "Github",
          "url": "https://github.com/eiriarte/voluntariado"
        },
        {
          "anchor": "Screencast",
          "url": "https://www.youtube.com/watch?v=oJzJS9lr6U4"
        }
      ]
    },
    {
      "id": "timed",
      "screenshot": "timed.png",
      "title": "Timed TODO App",
      "position": "Personal project",
      "description": "Multi-platform productivity app (timed TODO lists).",
      "skills": ["JavaScript", "React", "Electron", "Sass"],
      "keywords": ["F"],
      "links": [
        {
          "anchor": "Github",
          "url": "https://github.com/eiriarte/timed-todo"
        }
      ]
    }
  ],
  "es": [
    {
      "id": "cv",
      "screenshot": "cv.png",
      "title": "Mi CV y porfolio",
      "position": "Proyecto personal",
      "description": "Esta misma web. Utiliza mi componente i18nResume para permitir cambiar el idioma y filtrar los datos.",
      "skills": ["React", "TypeScript", "Material UI"],
      "keywords": ["F"],
      "links": [
        {
          "anchor": "Github",
          "url": "https://github.com/eiriarte/cv"
        }
      ]
    },
    {
      "id": "i18nresume",
      "screenshot": "i18nresume.png",
      "title": "i18nResume",
      "position": "Proyecto personal",
      "description": "Componente React de código abierto que puedes usar para representar datos de CV en formato json-resume con funcionalidad i18n y de filtrado.",
      "skills": ["React", "TypeScript", "Tailwind CSS"],
      "keywords": ["F"],
      "links": [
        {
          "anchor": "npm",
          "url": "https://www.npmjs.com/package/i18nresume"
        },
        {
          "anchor": "Github",
          "url": "https://github.com/eiriarte/i18nresume"
        }
      ]
    },
    {
      "id": "kongreso",
      "screenshot": "kongreso.png",
      "title": "Web de congreso",
      "position": "Proyecto no lucrativo",
      "description": "Sitio web oficial del Congreso Español de Esperanto de 2023.",
      "skills": ["JavaScript", "Bootstrap", "PHP", "Symfony", "Doctrine", "MySQL"],
      "keywords": ["B", "F"],
      "links": [
        {
          "anchor": "Web",
          "url": "https://kongreso.esperantosevilla.org"
        },
        {
          "anchor": "Github",
          "url": "https://github.com/eiriarte/hk2023"
        }
      ]
    },
    {
      "id": "ase",
      "screenshot": "ASE.png",
      "title": "Web oficial de ONG",
      "position": "Proyecto no lucrativo",
      "description": "Portal bilingüe de la Asociación Sevillana de Esperanto. Tema de WordPress a medida.",
      "skills": ["PHP", "WordPress", "JavaScript", "Sass"],
      "keywords": ["F", "B"],
      "links": [
        {
          "anchor": "Web",
          "url": "https://esperantosevilla.org/"
        }
      ]
    },
    {
      "id": "entrellaves",
      "screenshot": "entrellaves.png",
      "title": "Blog de programación",
      "position": "Proyecto personal",
      "description": "Mi blog personal sobre desarrollo web. Plugin de WordPress a medida.",
      "skills": ["PHP", "WordPress", "Apache", "Nginx"],
      "keywords": ["B"],
      "links": [
        {
          "anchor": "Web",
          "url": "https://entrellaves.com"
        }
      ]
    },
    {
      "id": "fch",
      "screenshot": "fch.png",
      "title": "Web de humor",
      "position": "Proyecto paralelo",
      "description": "Web de humor con servidor Node.js + MongoDB (anteriormente PHP, MySQL y Backbone.js).",
      "skills": ["Node.js", "Express", "MongoDB", "Sass", "PHP", "MySQL", "Backbone.js"],
      "keywords": ["F", "B"],
      "links": [
        {
          "anchor": "Web",
          "url": "https://nosolochistes.com/"
        },
        {
          "anchor": "Versión 2009",
          "url": "https://web.archive.org/web/20091207071245/http://feti-chistes.es/"
        },
        {
          "anchor": "Github",
          "url": "https://github.com/eiriarte/nosolochistes"
        }
      ]
    },
    {
      "id": "sng",
      "screenshot": "SNG.png",
      "title": "Web educativa",
      "position": "Proyecto personal",
      "description": "Web bilingüe educativa para estudiantes de español. Alojado en Amazon S3 y CloudFront.",
      "skills": ["JavaScript", "CSS", "Node.js", "AWS"],
      "keywords": ["F", "B"],
      "links": [
        {
          "anchor": "Web",
          "url": "https://spanishnumbers.guide"
        }
      ]
    },
    {
      "id": "numeros",
      "screenshot": "numeros.jpg",
      "title": "App educativa",
      "position": "Proyecto paralelo",
      "description": "Aplicación Android/iOS educativa para estudiantes de español.",
      "skills": ["React", "React Native"],
      "keywords": ["F"],
      "links": [
        {
          "anchor": "Github",
          "url": "https://github.com/eiriarte/numeros"
        }
      ]
    },
    {
      "id": "vivaverbo",
      "screenshot": "vivaverbo.png",
      "title": "Web-app educativa",
      "description": "Herramienta multiusuario para el aprendizaje de idiomas basada repetición espaciada.",
      "position": "Proyecto personal",
      "skills": ["JavaScript", "AngularJS", "Node.js", "MongoDB"],
      "keywords": ["F", "B"],
      "links": [
        {
          "anchor": "Github",
          "url": "https://github.com/eiriarte/vivaverbo"
        },
        {
          "anchor": "Vídeo",
          "url": "https://www.youtube.com/watch?v=1BSoZN3Uly8"
        }
      ]
    },
    {
      "id": "andex",
      "screenshot": "andex.png",
      "title": "Web-app para ONG",
      "position": "Proyecto no lucrativo",
      "description": "Aplicación web para gestionar los grupos de voluntarios de la asociación ANDEX.",
      "skills": ["CoffeScript", "AngularJS", "Node.js", "Express", "MongoDB", "Sass"],
      "keywords": ["F", "B"],
      "links": [
        {
          "anchor": "Github",
          "url": "https://github.com/eiriarte/voluntariado"
        },
        {
          "anchor": "Vídeo",
          "url": "https://www.youtube.com/watch?v=oJzJS9lr6U4"
        }
      ]
    },
    {
      "id": "timed",
      "screenshot": "timed.png",
      "title": "Gestor de tareas",
      "position": "Proyecto personal",
      "description": "Aplicación multiplataforma de productividad (listas de tareas cronometradas).",
      "skills": ["JavaScript", "React", "Electron", "Sass"],
      "keywords": ["F"],
      "links": [
        {
          "anchor": "Github",
          "url": "https://github.com/eiriarte/timed-todo"
        }
      ]
    }
  ]
}
